repo_flattener/__init__.py
repo_flattener/cache.py
repo_flattener/cli.py
repo_flattener/config.py
repo_flattener/core.py
repo_flattener/exceptions.py
repo_flattener-0.2.1.dist-info/licenses/LICENSE
tests/__init__.py
tests/test_repo_flattener.py
repo_flattener-0.2.1.dist-info/METADATA
repo_flattener-0.2.1.dist-info/WHEEL
repo_flattener-0.2.1.dist-info/entry_points.txt
repo_flattener-0.2.1.dist-info/top_level.txt
repo_flattener-0.2.1.dist-info/RECORD
