Metadata-Version: 2.4
Name: repo-flattener
Version: 0.2.1
Summary: A tool to convert a repository into flattened files for easier LLM upload
Author-email: Akash Chavan <achavan1211@gmail.com>
License: MIT
Project-URL: Homepage, https://github.com/CruiseDevice/repo-flattener
Project-URL: Bug Tracker, https://github.com/CruiseDevice/repo-flattener/issues
Classifier: Programming Language :: Python :: 3
Classifier: License :: OSI Approved :: MIT License
Classifier: Operating System :: OS Independent
Requires-Python: >=3.6
License-File: LICENSE
Requires-Dist: pyyaml>=5.1
Requires-Dist: tqdm>=4.62.0
Provides-Extra: dev
Requires-Dist: pytest>=7.0; extra == "dev"
Requires-Dist: pytest-cov>=4.0; extra == "dev"
Dynamic: license-file
Dynamic: requires-python
